Picked up JAVA_TOOL_OPTIONS: -Dstdout.encoding=UTF-8 -Dstderr.encoding=UTF-8
Compiled from "UnifiedTerminalGui.java"
public class com.chestterminal.gui.UnifiedTerminalGui extends com.hypixel.hytale.server.core.entity.entities.player.pages.InteractiveCustomUIPage<com.chestterminal.gui.UnifiedTerminalGui$TerminalGuiData> {
  private java.lang.String searchQuery;

  private java.util.HashMap<java.lang.String, java.lang.Integer> nearbyItems;

  private final java.util.Map<java.lang.String, com.hypixel.hytale.server.core.asset.type.item.config.Item> visibleItems;

  private boolean isSearchMode;

  private final com.hypixel.hytale.server.core.inventory.container.ItemContainer terminalInventory;

  private final com.hypixel.hytale.math.vector.Vector3i blockPosition;

  static final boolean $assertionsDisabled;

  public com.chestterminal.gui.UnifiedTerminalGui(com.hypixel.hytale.server.core.universe.PlayerRef, com.hypixel.hytale.protocol.packets.interface_.CustomPageLifetime, com.hypixel.hytale.server.core.inventory.container.ItemContainer, com.hypixel.hytale.math.vector.Vector3i, java.util.HashMap<java.lang.String, java.lang.Integer>);
    Code:
         0: aload_0
         1: aload_1
         2: aload_2
         3: getstatic     #1                  // Field com/chestterminal/gui/UnifiedTerminalGui$TerminalGuiData.CODEC:Lcom/hypixel/hytale/codec/builder/BuilderCodec;
         6: invokespecial #7                  // Method com/hypixel/hytale/server/core/entity/entities/player/pages/InteractiveCustomUIPage."<init>":(Lcom/hypixel/hytale/server/core/universe/PlayerRef;Lcom/hypixel/hytale/protocol/packets/interface_/CustomPageLifetime;Lcom/hypixel/hytale/codec/builder/BuilderCodec;)V
         9: aload_0
        10: ldc           #13                 // String
        12: putfield      #15                 // Field searchQuery:Ljava/lang/String;
        15: aload_0
        16: new           #21                 // class java/util/LinkedHashMap
        19: dup
        20: invokespecial #23                 // Method java/util/LinkedHashMap."<init>":()V
        23: putfield      #26                 // Field visibleItems:Ljava/util/Map;
        26: aload_0
        27: iconst_0
        28: putfield      #30                 // Field isSearchMode:Z
        31: aload_0
        32: aload_3
        33: putfield      #34                 // Field terminalInventory:Lcom/hypixel/hytale/server/core/inventory/container/ItemContainer;
        36: aload_0
        37: aload         4
        39: putfield      #38                 // Field blockPosition:Lcom/hypixel/hytale/math/vector/Vector3i;
        42: aload_0
        43: aload         5
        45: putfield      #42                 // Field nearbyItems:Ljava/util/HashMap;
        48: return

  public void build(com.hypixel.hytale.component.Ref<com.hypixel.hytale.server.core.universe.world.storage.EntityStore>, com.hypixel.hytale.server.core.ui.builder.UICommandBuilder, com.hypixel.hytale.server.core.ui.builder.UIEventBuilder, com.hypixel.hytale.component.Store<com.hypixel.hytale.server.core.universe.world.storage.EntityStore>);
    Code:
         0: aload_2
         1: ldc           #46                 // String Pages/DasEric_ChestTerminal_UnifiedGui.ui
         3: invokevirtual #48                 // Method com/hypixel/hytale/server/core/ui/builder/UICommandBuilder.append:(Ljava/lang/String;)Lcom/hypixel/hytale/server/core/ui/builder/UICommandBuilder;
         6: pop
         7: aload_2
         8: ldc           #54                 // String #StorageModeButton.Visible
        10: aload_0
        11: getfield      #30                 // Field isSearchMode:Z
        14: invokevirtual #56                 // Method com/hypixel/hytale/server/core/ui/builder/UICommandBuilder.set:(Ljava/lang/String;Z)Lcom/hypixel/hytale/server/core/ui/builder/UICommandBuilder;
        17: pop
        18: aload_2
        19: ldc           #60                 // String #SearchModeButton.Visible
        21: aload_0
        22: getfield      #30                 // Field isSearchMode:Z
        25: ifne          32
        28: iconst_1
        29: goto          33
        32: iconst_0
        33: invokevirtual #56                 // Method com/hypixel/hytale/server/core/ui/builder/UICommandBuilder.set:(Ljava/lang/String;Z)Lcom/hypixel/hytale/server/core/ui/builder/UICommandBuilder;
        36: pop
        37: aload_3
        38: getstatic     #62                 // Field com/hypixel/hytale/protocol/packets/interface_/CustomUIEventBindingType.Activating:Lcom/hypixel/hytale/protocol/packets/interface_/CustomUIEventBindingType;
        41: ldc           #68                 // String #StorageModeButton
        43: ldc           #70                 // String SwitchMode
        45: ldc           #72                 // String storage
        47: invokestatic  #74                 // Method com/hypixel/hytale/server/core/ui/builder/EventData.of:(Ljava/lang/String;Ljava/lang/String;)Lcom/hypixel/hytale/server/core/ui/builder/EventData;
        50: iconst_0
        51: invokevirtual #80                 // Method com/hypixel/hytale/server/core/ui/builder/UIEventBuilder.addEventBinding:(Lcom/hypixel/hytale/protocol/packets/interface_/CustomUIEventBindingType;Ljava/lang/String;Lcom/hypixel/hytale/server/core/ui/builder/EventData;Z)Lcom/hypixel/hytale/server/core/ui/builder/UIEventBuilder;
        54: pop
        55: aload_3
        56: getstatic     #62                 // Field com/hypixel/hytale/protocol/packets/interface_/CustomUIEventBindingType.Activating:Lcom/hypixel/hytale/protocol/packets/interface_/CustomUIEventBindingType;
        59: ldc           #86                 // String #SearchModeButton
        61: ldc           #70                 // String SwitchMode
        63: ldc           #88                 // String search
        65: invokestatic  #74                 // Method com/hypixel/hytale/server/core/ui/builder/EventData.of:(Ljava/lang/String;Ljava/lang/String;)Lcom/hypixel/hytale/server/core/ui/builder/EventData;
        68: iconst_0
        69: invokevirtual #80                 // Method com/hypixel/hytale/server/core/ui/builder/UIEventBuilder.addEventBinding:(Lcom/hypixel/hytale/protocol/packets/interface_/CustomUIEventBindingType;Ljava/lang/String;Lcom/hypixel/hytale/server/core/ui/builder/EventData;Z)Lcom/hypixel/hytale/server/core/ui/builder/UIEventBuilder;
        72: pop
        73: aload_0
        74: getfield      #30                 // Field isSearchMode:Z
        77: ifeq          137
        80: aload_2
        81: ldc           #90                 // String #SearchSection.Visible
        83: iconst_1
        84: invokevirtual #56                 // Method com/hypixel/hytale/server/core/ui/builder/UICommandBuilder.set:(Ljava/lang/String;Z)Lcom/hypixel/hytale/server/core/ui/builder/UICommandBuilder;
        87: pop
        88: aload_2
        89: ldc           #92                 // String #StorageSection.Visible
        91: iconst_0
        92: invokevirtual #56                 // Method com/hypixel/hytale/server/core/ui/builder/UICommandBuilder.set:(Ljava/lang/String;Z)Lcom/hypixel/hytale/server/core/ui/builder/UICommandBuilder;
        95: pop
        96: aload_2
        97: ldc           #94                 // String #SearchInput.Value
        99: aload_0
       100: getfield      #15                 // Field searchQuery:Ljava/lang/String;
       103: invokevirtual #96                 // Method com/hypixel/hytale/server/core/ui/builder/UICommandBuilder.set:(Ljava/lang/String;Ljava/lang/String;)Lcom/hypixel/hytale/server/core/ui/builder/UICommandBuilder;
       106: pop
       107: aload_3
       108: getstatic     #99                 // Field com/hypixel/hytale/protocol/packets/interface_/CustomUIEventBindingType.ValueChanged:Lcom/hypixel/hytale/protocol/packets/interface_/CustomUIEventBindingType;
       111: ldc           #102                // String #SearchInput
       113: ldc           #104                // String @SearchQuery
       115: ldc           #94                 // String #SearchInput.Value
       117: invokestatic  #74                 // Method com/hypixel/hytale/server/core/ui/builder/EventData.of:(Ljava/lang/String;Ljava/lang/String;)Lcom/hypixel/hytale/server/core/ui/builder/EventData;
       120: iconst_0
       121: invokevirtual #80                 // Method com/hypixel/hytale/server/core/ui/builder/UIEventBuilder.addEventBinding:(Lcom/hypixel/hytale/protocol/packets/interface_/CustomUIEventBindingType;Ljava/lang/String;Lcom/hypixel/hytale/server/core/ui/builder/EventData;Z)Lcom/hypixel/hytale/server/core/ui/builder/UIEventBuilder;
       124: pop
       125: aload_0
       126: aload_1
       127: aload_2
       128: aload_3
       129: aload         4
       131: invokevirtual #106                // Method buildSearchList:(Lcom/hypixel/hytale/component/Ref;Lcom/hypixel/hytale/server/core/ui/builder/UICommandBuilder;Lcom/hypixel/hytale/server/core/ui/builder/UIEventBuilder;Lcom/hypixel/hytale/component/ComponentAccessor;)V
       134: goto          162
       137: aload_2
       138: ldc           #90                 // String #SearchSection.Visible
       140: iconst_0
       141: invokevirtual #56                 // Method com/hypixel/hytale/server/core/ui/builder/UICommandBuilder.set:(Ljava/lang/String;Z)Lcom/hypixel/hytale/server/core/ui/builder/UICommandBuilder;
       144: pop
       145: aload_2
       146: ldc           #92                 // String #StorageSection.Visible
       148: iconst_1
       149: invokevirtual #56                 // Method com/hypixel/hytale/server/core/ui/builder/UICommandBuilder.set:(Ljava/lang/String;Z)Lcom/hypixel/hytale/server/core/ui/builder/UICommandBuilder;
       152: pop
       153: aload_0
       154: aload_1
       155: aload_2
       156: aload_3
       157: aload         4
       159: invokevirtual #110                // Method buildStorageView:(Lcom/hypixel/hytale/component/Ref;Lcom/hypixel/hytale/server/core/ui/builder/UICommandBuilder;Lcom/hypixel/hytale/server/core/ui/builder/UIEventBuilder;Lcom/hypixel/hytale/component/Store;)V
       162: return

  public void handleDataEvent(com.hypixel.hytale.component.Ref<com.hypixel.hytale.server.core.universe.world.storage.EntityStore>, com.hypixel.hytale.component.Store<com.hypixel.hytale.server.core.universe.world.storage.EntityStore>, com.chestterminal.gui.UnifiedTerminalGui$TerminalGuiData);
    Code:
         0: aload_0
         1: aload_1
         2: aload_2
         3: aload_3
         4: invokespecial #114                // Method com/hypixel/hytale/server/core/entity/entities/player/pages/InteractiveCustomUIPage.handleDataEvent:(Lcom/hypixel/hytale/component/Ref;Lcom/hypixel/hytale/component/Store;Ljava/lang/Object;)V
         7: aload_3
         8: getfield      #118                // Field com/chestterminal/gui/UnifiedTerminalGui$TerminalGuiData.switchMode:Ljava/lang/String;
        11: ifnull        65
        14: aload_0
        15: aload_3
        16: getfield      #118                // Field com/chestterminal/gui/UnifiedTerminalGui$TerminalGuiData.switchMode:Ljava/lang/String;
        19: ldc           #88                 // String search
        21: invokevirtual #121                // Method java/lang/String.equals:(Ljava/lang/Object;)Z
        24: putfield      #30                 // Field isSearchMode:Z
        27: new           #49                 // class com/hypixel/hytale/server/core/ui/builder/UICommandBuilder
        30: dup
        31: invokespecial #127                // Method com/hypixel/hytale/server/core/ui/builder/UICommandBuilder."<init>":()V
        34: astore        4
        36: new           #81                 // class com/hypixel/hytale/server/core/ui/builder/UIEventBuilder
        39: dup
        40: invokespecial #128                // Method com/hypixel/hytale/server/core/ui/builder/UIEventBuilder."<init>":()V
        43: astore        5
        45: aload_0
        46: aload_1
        47: aload         4
        49: aload         5
        51: aload_2
        52: invokevirtual #129                // Method build:(Lcom/hypixel/hytale/component/Ref;Lcom/hypixel/hytale/server/core/ui/builder/UICommandBuilder;Lcom/hypixel/hytale/server/core/ui/builder/UIEventBuilder;Lcom/hypixel/hytale/component/Store;)V
        55: aload_0
        56: aload         4
        58: aload         5
        60: iconst_0
        61: invokevirtual #132                // Method sendUpdate:(Lcom/hypixel/hytale/server/core/ui/builder/UICommandBuilder;Lcom/hypixel/hytale/server/core/ui/builder/UIEventBuilder;Z)V
        64: return
        65: aload_3
        66: getfield      #136                // Field com/chestterminal/gui/UnifiedTerminalGui$TerminalGuiData.findItem:Ljava/lang/String;
        69: ifnull        102
        72: aload_0
        73: aload_2
        74: invokevirtual #139                // Method com/hypixel/hytale/component/Store.getExternalData:()Ljava/lang/Object;
        77: checkcast     #145                // class com/hypixel/hytale/server/core/universe/world/storage/EntityStore
        80: invokevirtual #147                // Method com/hypixel/hytale/server/core/universe/world/storage/EntityStore.getWorld:()Lcom/hypixel/hytale/server/core/universe/world/World;
        83: aload_1
        84: aload_2
        85: getstatic     #151                // Field com/chestterminal/ChestTerminalPlugin.CONFIG:Lcom/chestterminal/config/ChestTerminalConfig;
        88: invokevirtual #157                // Method com/chestterminal/config/ChestTerminalConfig.getSearchRadius:()I
        91: aload_3
        92: getfield      #136                // Field com/chestterminal/gui/UnifiedTerminalGui$TerminalGuiData.findItem:Ljava/lang/String;
        95: invokevirtual #163                // Method notifyNearbyItems:(Lcom/hypixel/hytale/server/core/universe/world/World;Lcom/hypixel/hytale/component/Ref;Lcom/hypixel/hytale/component/Store;ILjava/lang/String;)V
        98: aload_0
        99: invokevirtual #167                // Method close:()V
       102: aload_3
       103: getfield      #170                // Field com/chestterminal/gui/UnifiedTerminalGui$TerminalGuiData.getItem:Ljava/lang/String;
       106: ifnull        223
       109: aload_3
       110: getfield      #170                // Field com/chestterminal/gui/UnifiedTerminalGui$TerminalGuiData.getItem:Ljava/lang/String;
       113: ldc           #173                // String :
       115: invokevirtual #175                // Method java/lang/String.split:(Ljava/lang/String;)[Ljava/lang/String;
       118: astore        4
       120: aload         4
       122: iconst_0
       123: aaload
       124: astore        5
       126: aload         4
       128: iconst_1
       129: aaload
       130: invokestatic  #179                // Method java/lang/Integer.parseInt:(Ljava/lang/String;)I
       133: istore        6
       135: aload_0
       136: aload_2
       137: invokevirtual #139                // Method com/hypixel/hytale/component/Store.getExternalData:()Ljava/lang/Object;
       140: checkcast     #145                // class com/hypixel/hytale/server/core/universe/world/storage/EntityStore
       143: invokevirtual #147                // Method com/hypixel/hytale/server/core/universe/world/storage/EntityStore.getWorld:()Lcom/hypixel/hytale/server/core/universe/world/World;
       146: aload_1
       147: aload_2
       148: getstatic     #151                // Field com/chestterminal/ChestTerminalPlugin.CONFIG:Lcom/chestterminal/config/ChestTerminalConfig;
       151: invokevirtual #157                // Method com/chestterminal/config/ChestTerminalConfig.getSearchRadius:()I
       154: aload         5
       156: iload         6
       158: invokevirtual #185                // Method extractItems:(Lcom/hypixel/hytale/server/core/universe/world/World;Lcom/hypixel/hytale/component/Ref;Lcom/hypixel/hytale/component/Store;ILjava/lang/String;I)V
       161: aload_0
       162: aload_2
       163: invokevirtual #139                // Method com/hypixel/hytale/component/Store.getExternalData:()Ljava/lang/Object;
       166: checkcast     #145                // class com/hypixel/hytale/server/core/universe/world/storage/EntityStore
       169: invokevirtual #147                // Method com/hypixel/hytale/server/core/universe/world/storage/EntityStore.getWorld:()Lcom/hypixel/hytale/server/core/universe/world/World;
       172: aload_1
       173: aload_2
       174: getstatic     #151                // Field com/chestterminal/ChestTerminalPlugin.CONFIG:Lcom/chestterminal/config/ChestTerminalConfig;
       177: invokevirtual #157                // Method com/chestterminal/config/ChestTerminalConfig.getSearchRadius:()I
       180: invokestatic  #189                // Method com/chestterminal/util/InventoryUtils.collectNearbyItems:(Lcom/hypixel/hytale/server/core/universe/world/World;Lcom/hypixel/hytale/component/Ref;Lcom/hypixel/hytale/component/Store;I)Ljava/util/HashMap;
       183: putfield      #42                 // Field nearbyItems:Ljava/util/HashMap;
       186: new           #49                 // class com/hypixel/hytale/server/core/ui/builder/UICommandBuilder
       189: dup
       190: invokespecial #127                // Method com/hypixel/hytale/server/core/ui/builder/UICommandBuilder."<init>":()V
       193: astore        7
       195: new           #81                 // class com/hypixel/hytale/server/core/ui/builder/UIEventBuilder
       198: dup
       199: invokespecial #128                // Method com/hypixel/hytale/server/core/ui/builder/UIEventBuilder."<init>":()V
       202: astore        8
       204: aload_0
       205: aload_1
       206: aload         7
       208: aload         8
       210: aload_2
       211: invokevirtual #106                // Method buildSearchList:(Lcom/hypixel/hytale/component/Ref;Lcom/hypixel/hytale/server/core/ui/builder/UICommandBuilder;Lcom/hypixel/hytale/server/core/ui/builder/UIEventBuilder;Lcom/hypixel/hytale/component/ComponentAccessor;)V
       214: aload_0
       215: aload         7
       217: aload         8
       219: iconst_0
       220: invokevirtual #132                // Method sendUpdate:(Lcom/hypixel/hytale/server/core/ui/builder/UICommandBuilder;Lcom/hypixel/hytale/server/core/ui/builder/UIEventBuilder;Z)V
       223: aload_3
       224: getfield      #195                // Field com/chestterminal/gui/UnifiedTerminalGui$TerminalGuiData.searchQuery:Ljava/lang/String;
       227: ifnull        281
       230: aload_0
       231: aload_3
       232: getfield      #195                // Field com/chestterminal/gui/UnifiedTerminalGui$TerminalGuiData.searchQuery:Ljava/lang/String;
       235: invokevirtual #196                // Method java/lang/String.trim:()Ljava/lang/String;
       238: invokevirtual #200                // Method java/lang/String.toLowerCase:()Ljava/lang/String;
       241: putfield      #15                 // Field searchQuery:Ljava/lang/String;
       244: new           #49                 // class com/hypixel/hytale/server/core/ui/builder/UICommandBuilder
       247: dup
       248: invokespecial #127                // Method com/hypixel/hytale/server/core/ui/builder/UICommandBuilder."<init>":()V
       251: astore        4
       253: new           #81                 // class com/hypixel/hytale/server/core/ui/builder/UIEventBuilder
       256: dup
       257: invokespecial #128                // Method com/hypixel/hytale/server/core/ui/builder/UIEventBuilder."<init>":()V
       260: astore        5
       262: aload_0
       263: aload_1
       264: aload         4
       266: aload         5
       268: aload_2
       269: invokevirtual #106                // Method buildSearchList:(Lcom/hypixel/hytale/component/Ref;Lcom/hypixel/hytale/server/core/ui/builder/UICommandBuilder;Lcom/hypixel/hytale/server/core/ui/builder/UIEventBuilder;Lcom/hypixel/hytale/component/ComponentAccessor;)V
       272: aload_0
       273: aload         4
       275: aload         5
       277: iconst_0
       278: invokevirtual #132                // Method sendUpdate:(Lcom/hypixel/hytale/server/core/ui/builder/UICommandBuilder;Lcom/hypixel/hytale/server/core/ui/builder/UIEventBuilder;Z)V
       281: return

  private void buildStorageView(com.hypixel.hytale.component.Ref<com.hypixel.hytale.server.core.universe.world.storage.EntityStore>, com.hypixel.hytale.server.core.ui.builder.UICommandBuilder, com.hypixel.hytale.server.core.ui.builder.UIEventBuilder, com.hypixel.hytale.component.Store<com.hypixel.hytale.server.core.universe.world.storage.EntityStore>);
    Code:
         0: aload_2
         1: ldc           #203                // String #StorageInfo.Text
         3: ldc           #205                // String Place items here to distribute them to nearby chests
         5: invokevirtual #96                 // Method com/hypixel/hytale/server/core/ui/builder/UICommandBuilder.set:(Ljava/lang/String;Ljava/lang/String;)Lcom/hypixel/hytale/server/core/ui/builder/UICommandBuilder;
         8: pop
         9: iconst_0
        10: istore        5
        12: iconst_0
        13: istore        6
        15: iload         6
        17: aload_0
        18: getfield      #34                 // Field terminalInventory:Lcom/hypixel/hytale/server/core/inventory/container/ItemContainer;
        21: invokevirtual #207                // Method com/hypixel/hytale/server/core/inventory/container/ItemContainer.getCapacity:()S
        24: if_icmpge     64
        27: aload_0
        28: getfield      #34                 // Field terminalInventory:Lcom/hypixel/hytale/server/core/inventory/container/ItemContainer;
        31: iload         6
        33: invokevirtual #213                // Method com/hypixel/hytale/server/core/inventory/container/ItemContainer.getItemStack:(S)Lcom/hypixel/hytale/server/core/inventory/ItemStack;
        36: astore        7
        38: aload         7
        40: ifnull        54
        43: aload         7
        45: invokevirtual #217                // Method com/hypixel/hytale/server/core/inventory/ItemStack.isEmpty:()Z
        48: ifne          54
        51: iinc          5, 1
        54: iload         6
        56: iconst_1
        57: iadd
        58: i2s
        59: istore        6
        61: goto          15
        64: aload_2
        65: ldc           #223                // String #CapacityText.Text
        67: iload         5
        69: aload_0
        70: getfield      #34                 // Field terminalInventory:Lcom/hypixel/hytale/server/core/inventory/container/ItemContainer;
        73: invokevirtual #207                // Method com/hypixel/hytale/server/core/inventory/container/ItemContainer.getCapacity:()S
        76: invokedynamic #225,  0            // InvokeDynamic #0:makeConcatWithConstants:(IS)Ljava/lang/String;
        81: invokevirtual #96                 // Method com/hypixel/hytale/server/core/ui/builder/UICommandBuilder.set:(Ljava/lang/String;Ljava/lang/String;)Lcom/hypixel/hytale/server/core/ui/builder/UICommandBuilder;
        84: pop
        85: return

  private void buildSearchList(com.hypixel.hytale.component.Ref<com.hypixel.hytale.server.core.universe.world.storage.EntityStore>, com.hypixel.hytale.server.core.ui.builder.UICommandBuilder, com.hypixel.hytale.server.core.ui.builder.UIEventBuilder, com.hypixel.hytale.component.ComponentAccessor<com.hypixel.hytale.server.core.universe.world.storage.EntityStore>);
    Code:
         0: new           #21                 // class java/util/LinkedHashMap
         3: dup
         4: invokespecial #23                 // Method java/util/LinkedHashMap."<init>":()V
         7: astore        5
         9: aload_0
        10: getfield      #42                 // Field nearbyItems:Ljava/util/HashMap;
        13: aload         5
        15: invokedynamic #229,  0            // InvokeDynamic #1:accept:(Ljava/util/HashMap;)Ljava/util/function/BiConsumer;
        20: invokevirtual #233                // Method java/util/HashMap.forEach:(Ljava/util/function/BiConsumer;)V
        23: aload         4
        25: aload_1
        26: invokestatic  #239                // Method com/hypixel/hytale/server/core/entity/entities/Player.getComponentType:()Lcom/hypixel/hytale/component/ComponentType;
        29: invokeinterface #245,  3          // InterfaceMethod com/hypixel/hytale/component/ComponentAccessor.getComponent:(Lcom/hypixel/hytale/component/Ref;Lcom/hypixel/hytale/component/ComponentType;)Lcom/hypixel/hytale/component/Component;
        34: checkcast     #240                // class com/hypixel/hytale/server/core/entity/entities/Player
        37: astore        6
        39: getstatic     #251                // Field $assertionsDisabled:Z
        42: ifne          58
        45: aload         6
        47: ifnonnull     58
        50: new           #254                // class java/lang/AssertionError
        53: dup
        54: invokespecial #256                // Method java/lang/AssertionError."<init>":()V
        57: athrow
        58: aload_0
        59: getfield      #15                 // Field searchQuery:Ljava/lang/String;
        62: invokevirtual #257                // Method java/lang/String.isEmpty:()Z
        65: ifeq          91
        68: aload_0
        69: getfield      #26                 // Field visibleItems:Ljava/util/Map;
        72: invokeinterface #258,  1          // InterfaceMethod java/util/Map.clear:()V
        77: aload_0
        78: getfield      #26                 // Field visibleItems:Ljava/util/Map;
        81: aload         5
        83: invokeinterface #263,  2          // InterfaceMethod java/util/Map.putAll:(Ljava/util/Map;)V
        88: goto          435
        91: new           #267                // class it/unimi/dsi/fastutil/objects/ObjectArrayList
        94: dup
        95: invokespecial #269                // Method it/unimi/dsi/fastutil/objects/ObjectArrayList."<init>":()V
        98: astore        7
       100: aload         5
       102: invokevirtual #270                // Method java/util/HashMap.entrySet:()Ljava/util/Set;
       105: invokeinterface #274,  1          // InterfaceMethod java/util/Set.iterator:()Ljava/util/Iterator;
       110: astore        8
       112: aload         8
       114: invokeinterface #280,  1          // InterfaceMethod java/util/Iterator.hasNext:()Z
       119: ifeq          173
       122: aload         8
       124: invokeinterface #285,  1          // InterfaceMethod java/util/Iterator.next:()Ljava/lang/Object;
       129: checkcast     #288                // class java/util/Map$Entry
       132: astore        9
       134: aload         9
       136: invokeinterface #290,  1          // InterfaceMethod java/util/Map$Entry.getValue:()Ljava/lang/Object;
       141: ifnull        170
       144: aload         7
       146: new           #293                // class com/chestterminal/gui/UnifiedTerminalGui$SearchResult
       149: dup
       150: aload         9
       152: invokeinterface #295,  1          // InterfaceMethod java/util/Map$Entry.getKey:()Ljava/lang/Object;
       157: checkcast     #122                // class java/lang/String
       160: getstatic     #298                // Field com/hypixel/hytale/server/core/command/system/MatchResult.EXACT:Lcom/hypixel/hytale/server/core/command/system/MatchResult;
       163: invokespecial #304                // Method com/chestterminal/gui/UnifiedTerminalGui$SearchResult."<init>":(Ljava/lang/String;Lcom/hypixel/hytale/server/core/command/system/MatchResult;)V
       166: invokevirtual #307                // Method it/unimi/dsi/fastutil/objects/ObjectArrayList.add:(Ljava/lang/Object;)Z
       169: pop
       170: goto          112
       173: aload_0
       174: getfield      #15                 // Field searchQuery:Ljava/lang/String;
       177: ldc_w         #310                // String
       180: invokevirtual #175                // Method java/lang/String.split:(Ljava/lang/String;)[Ljava/lang/String;
       183: astore        8
       185: iconst_0
       186: istore        9
       188: iload         9
       190: aload         8
       192: arraylength
       193: if_icmpge     358
       196: aload         8
       198: iload         9
       200: aaload
       201: getstatic     #312                // Field java/util/Locale.ENGLISH:Ljava/util/Locale;
       204: invokevirtual #318                // Method java/lang/String.toLowerCase:(Ljava/util/Locale;)Ljava/lang/String;
       207: astore        10
       209: aload         7
       211: invokevirtual #321                // Method it/unimi/dsi/fastutil/objects/ObjectArrayList.size:()I
       214: iconst_1
       215: isub
       216: istore        11
       218: iload         11
       220: iflt          352
       223: aload         7
       225: iload         11
       227: invokevirtual #324                // Method it/unimi/dsi/fastutil/objects/ObjectArrayList.get:(I)Ljava/lang/Object;
       230: checkcast     #293                // class com/chestterminal/gui/UnifiedTerminalGui$SearchResult
       233: astore        12
       235: aload         5
       237: aload         12
       239: getfield      #328                // Field com/chestterminal/gui/UnifiedTerminalGui$SearchResult.name:Ljava/lang/String;
       242: invokevirtual #331                // Method java/util/HashMap.get:(Ljava/lang/Object;)Ljava/lang/Object;
       245: checkcast     #334                // class com/hypixel/hytale/server/core/asset/type/item/config/Item
       248: astore        13
       250: getstatic     #336                // Field com/hypixel/hytale/server/core/command/system/MatchResult.NONE:Lcom/hypixel/hytale/server/core/command/system/MatchResult;
       253: astore        14
       255: aload         13
       257: ifnull        312
       260: invokestatic  #339                // Method com/hypixel/hytale/server/core/modules/i18n/I18nModule.get:()Lcom/hypixel/hytale/server/core/modules/i18n/I18nModule;
       263: aload_0
       264: getfield      #344                // Field playerRef:Lcom/hypixel/hytale/server/core/universe/PlayerRef;
       267: invokevirtual #348                // Method com/hypixel/hytale/server/core/universe/PlayerRef.getLanguage:()Ljava/lang/String;
       270: aload         13
       272: invokevirtual #353                // Method com/hypixel/hytale/server/core/asset/type/item/config/Item.getTranslationKey:()Ljava/lang/String;
       275: invokevirtual #356                // Method com/hypixel/hytale/server/core/modules/i18n/I18nModule.getMessage:(Ljava/lang/String;Ljava/lang/String;)Ljava/lang/String;
       278: astore        15
       280: aload         15
       282: ifnull        307
       285: aload         15
       287: getstatic     #312                // Field java/util/Locale.ENGLISH:Ljava/util/Locale;
       290: invokevirtual #318                // Method java/lang/String.toLowerCase:(Ljava/util/Locale;)Ljava/lang/String;
       293: aload         10
       295: invokevirtual #360                // Method java/lang/String.contains:(Ljava/lang/CharSequence;)Z
       298: ifeq          307
       301: getstatic     #298                // Field com/hypixel/hytale/server/core/command/system/MatchResult.EXACT:Lcom/hypixel/hytale/server/core/command/system/MatchResult;
       304: goto          310
       307: getstatic     #336                // Field com/hypixel/hytale/server/core/command/system/MatchResult.NONE:Lcom/hypixel/hytale/server/core/command/system/MatchResult;
       310: astore        14
       312: aload         14
       314: getstatic     #336                // Field com/hypixel/hytale/server/core/command/system/MatchResult.NONE:Lcom/hypixel/hytale/server/core/command/system/MatchResult;
       317: if_acmpne     331
       320: aload         7
       322: iload         11
       324: invokevirtual #364                // Method it/unimi/dsi/fastutil/objects/ObjectArrayList.remove:(I)Ljava/lang/Object;
       327: pop
       328: goto          346
       331: aload         12
       333: aload         12
       335: getfield      #367                // Field com/chestterminal/gui/UnifiedTerminalGui$SearchResult.match:Lcom/hypixel/hytale/server/core/command/system/MatchResult;
       338: aload         14
       340: invokevirtual #370                // Method com/hypixel/hytale/server/core/command/system/MatchResult.min:(Lcom/hypixel/hytale/server/core/command/system/MatchResult;)Lcom/hypixel/hytale/server/core/command/system/MatchResult;
       343: putfield      #367                // Field com/chestterminal/gui/UnifiedTerminalGui$SearchResult.match:Lcom/hypixel/hytale/server/core/command/system/MatchResult;
       346: iinc          11, -1
       349: goto          218
       352: iinc          9, 1
       355: goto          188
       358: aload         7
       360: getstatic     #374                // Field com/chestterminal/gui/UnifiedTerminalGui$SearchResult.COMPARATOR:Ljava/util/Comparator;
       363: invokevirtual #378                // Method it/unimi/dsi/fastutil/objects/ObjectArrayList.sort:(Ljava/util/Comparator;)V
       366: aload_0
       367: getfield      #26                 // Field visibleItems:Ljava/util/Map;
       370: invokeinterface #258,  1          // InterfaceMethod java/util/Map.clear:()V
       375: aload         7
       377: invokevirtual #382                // Method it/unimi/dsi/fastutil/objects/ObjectArrayList.iterator:()Lit/unimi/dsi/fastutil/objects/ObjectListIterator;
       380: astore        9
       382: aload         9
       384: invokeinterface #280,  1          // InterfaceMethod java/util/Iterator.hasNext:()Z
       389: ifeq          435
       392: aload         9
       394: invokeinterface #285,  1          // InterfaceMethod java/util/Iterator.next:()Ljava/lang/Object;
       399: checkcast     #293                // class com/chestterminal/gui/UnifiedTerminalGui$SearchResult
       402: astore        10
       404: aload_0
       405: getfield      #26                 // Field visibleItems:Ljava/util/Map;
       408: aload         10
       410: getfield      #328                // Field com/chestterminal/gui/UnifiedTerminalGui$SearchResult.name:Ljava/lang/String;
       413: aload         5
       415: aload         10
       417: getfield      #328                // Field com/chestterminal/gui/UnifiedTerminalGui$SearchResult.name:Ljava/lang/String;
       420: invokevirtual #331                // Method java/util/HashMap.get:(Ljava/lang/Object;)Ljava/lang/Object;
       423: checkcast     #334                // class com/hypixel/hytale/server/core/asset/type/item/config/Item
       426: invokeinterface #385,  3          // InterfaceMethod java/util/Map.put:(Ljava/lang/Object;Ljava/lang/Object;)Ljava/lang/Object;
       431: pop
       432: goto          382
       435: aload_0
       436: aload_0
       437: getfield      #26                 // Field visibleItems:Ljava/util/Map;
       440: aload         6
       442: aload_2
       443: aload_3
       444: invokevirtual #389                // Method buildSearchButtons:(Ljava/util/Map;Lcom/hypixel/hytale/server/core/entity/entities/Player;Lcom/hypixel/hytale/server/core/ui/builder/UICommandBuilder;Lcom/hypixel/hytale/server/core/ui/builder/UIEventBuilder;)V
       447: return

  private void buildSearchButtons(java.util.Map<java.lang.String, com.hypixel.hytale.server.core.asset.type.item.config.Item>, com.hypixel.hytale.server.core.entity.entities.Player, com.hypixel.hytale.server.core.ui.builder.UICommandBuilder, com.hypixel.hytale.server.core.ui.builder.UIEventBuilder);
    Code:
         0: aload_3
         1: ldc_w         #393                // String #ItemCards
         4: invokevirtual #395                // Method com/hypixel/hytale/server/core/ui/builder/UICommandBuilder.clear:(Ljava/lang/String;)Lcom/hypixel/hytale/server/core/ui/builder/UICommandBuilder;
         7: pop
         8: aload_3
         9: ldc_w         #397                // String #ItemSection.Visible
        12: iconst_1
        13: invokevirtual #56                 // Method com/hypixel/hytale/server/core/ui/builder/UICommandBuilder.set:(Ljava/lang/String;Z)Lcom/hypixel/hytale/server/core/ui/builder/UICommandBuilder;
        16: pop
        17: iconst_0
        18: istore        5
        20: iconst_0
        21: istore        6
        23: aload_1
        24: invokeinterface #399,  1          // InterfaceMethod java/util/Map.entrySet:()Ljava/util/Set;
        29: invokeinterface #274,  1          // InterfaceMethod java/util/Set.iterator:()Ljava/util/Iterator;
        34: astore        7
        36: aload         7
        38: invokeinterface #280,  1          // InterfaceMethod java/util/Iterator.hasNext:()Z
        43: ifeq          426
        46: aload         7
        48: invokeinterface #285,  1          // InterfaceMethod java/util/Iterator.next:()Ljava/lang/Object;
        53: checkcast     #288                // class java/util/Map$Entry
        56: astore        8
        58: aload         8
        60: invokeinterface #290,  1          // InterfaceMethod java/util/Map$Entry.getValue:()Ljava/lang/Object;
        65: checkcast     #334                // class com/hypixel/hytale/server/core/asset/type/item/config/Item
        68: astore        9
        70: aload         9
        72: ifnonnull     78
        75: goto          36
        78: iload         6
        80: ifne          94
        83: aload_3
        84: ldc_w         #393                // String #ItemCards
        87: ldc_w         #400                // String Group { LayoutMode: Left; Anchor: (Bottom: 0); }
        90: invokevirtual #402                // Method com/hypixel/hytale/server/core/ui/builder/UICommandBuilder.appendInline:(Ljava/lang/String;Ljava/lang/String;)Lcom/hypixel/hytale/server/core/ui/builder/UICommandBuilder;
        93: pop
        94: aload_3
        95: iload         5
        97: invokedynamic #405,  0            // InvokeDynamic #2:makeConcatWithConstants:(I)Ljava/lang/String;
       102: ldc_w         #408                // String Pages/DasEric_ChestTerminal_SearchItemIcon.ui
       105: invokevirtual #410                // Method com/hypixel/hytale/server/core/ui/builder/UICommandBuilder.append:(Ljava/lang/String;Ljava/lang/String;)Lcom/hypixel/hytale/server/core/ui/builder/UICommandBuilder;
       108: pop
       109: invokestatic  #412                // Method com/chestterminal/util/MessageHelper.multiLine:()Lcom/chestterminal/util/MessageHelper$ML;
       112: astore        10
       114: aload         10
       116: aload         9
       118: invokevirtual #353                // Method com/hypixel/hytale/server/core/asset/type/item/config/Item.getTranslationKey:()Ljava/lang/String;
       121: invokestatic  #418                // Method com/hypixel/hytale/server/core/Message.translation:(Ljava/lang/String;)Lcom/hypixel/hytale/server/core/Message;
       124: iconst_1
       125: invokevirtual #424                // Method com/hypixel/hytale/server/core/Message.bold:(Z)Lcom/hypixel/hytale/server/core/Message;
       128: invokevirtual #428                // Method com/chestterminal/util/MessageHelper$ML.append:(Lcom/hypixel/hytale/server/core/Message;)Lcom/chestterminal/util/MessageHelper$ML;
       131: invokevirtual #433                // Method com/chestterminal/util/MessageHelper$ML.nl:()Lcom/chestterminal/util/MessageHelper$ML;
       134: pop
       135: aload         10
       137: aload_0
       138: getfield      #42                 // Field nearbyItems:Ljava/util/HashMap;
       141: aload         8
       143: invokeinterface #295,  1          // InterfaceMethod java/util/Map$Entry.getKey:()Ljava/lang/Object;
       148: iconst_0
       149: invokestatic  #436                // Method java/lang/Integer.valueOf:(I)Ljava/lang/Integer;
       152: invokevirtual #440                // Method java/util/HashMap.getOrDefault:(Ljava/lang/Object;Ljava/lang/Object;)Ljava/lang/Object;
       155: invokestatic  #443                // Method java/lang/String.valueOf:(Ljava/lang/Object;)Ljava/lang/String;
       158: invokedynamic #446,  0            // InvokeDynamic #3:makeConcatWithConstants:(Ljava/lang/String;)Ljava/lang/String;
       163: invokestatic  #449                // Method com/hypixel/hytale/server/core/Message.raw:(Ljava/lang/String;)Lcom/hypixel/hytale/server/core/Message;
       166: invokevirtual #428                // Method com/chestterminal/util/MessageHelper$ML.append:(Lcom/hypixel/hytale/server/core/Message;)Lcom/chestterminal/util/MessageHelper$ML;
       169: pop
       170: aload_3
       171: iload         5
       173: iload         6
       175: invokedynamic #452,  0            // InvokeDynamic #4:makeConcatWithConstants:(II)Ljava/lang/String;
       180: aload         10
       182: invokevirtual #455                // Method com/chestterminal/util/MessageHelper$ML.build:()Lcom/hypixel/hytale/server/core/Message;
       185: invokevirtual #458                // Method com/hypixel/hytale/server/core/ui/builder/UICommandBuilder.set:(Ljava/lang/String;Lcom/hypixel/hytale/server/core/Message;)Lcom/hypixel/hytale/server/core/ui/builder/UICommandBuilder;
       188: pop
       189: aload_3
       190: iload         5
       192: iload         6
       194: invokedynamic #461,  0            // InvokeDynamic #5:makeConcatWithConstants:(II)Ljava/lang/String;
       199: aload         8
       201: invokeinterface #295,  1          // InterfaceMethod java/util/Map$Entry.getKey:()Ljava/lang/Object;
       206: checkcast     #122                // class java/lang/String
       209: invokevirtual #96                 // Method com/hypixel/hytale/server/core/ui/builder/UICommandBuilder.set:(Ljava/lang/String;Ljava/lang/String;)Lcom/hypixel/hytale/server/core/ui/builder/UICommandBuilder;
       212: pop
       213: aload_3
       214: iload         5
       216: iload         6
       218: invokedynamic #462,  0            // InvokeDynamic #6:makeConcatWithConstants:(II)Ljava/lang/String;
       223: aload         10
       225: invokevirtual #455                // Method com/chestterminal/util/MessageHelper$ML.build:()Lcom/hypixel/hytale/server/core/Message;
       228: invokevirtual #458                // Method com/hypixel/hytale/server/core/ui/builder/UICommandBuilder.set:(Ljava/lang/String;Lcom/hypixel/hytale/server/core/Message;)Lcom/hypixel/hytale/server/core/ui/builder/UICommandBuilder;
       231: pop
       232: aload_3
       233: iload         5
       235: iload         6
       237: invokedynamic #463,  0            // InvokeDynamic #7:makeConcatWithConstants:(II)Ljava/lang/String;
       242: aload_0
       243: getfield      #42                 // Field nearbyItems:Ljava/util/HashMap;
       246: aload         8
       248: invokeinterface #295,  1          // InterfaceMethod java/util/Map$Entry.getKey:()Ljava/lang/Object;
       253: iconst_0
       254: invokestatic  #436                // Method java/lang/Integer.valueOf:(I)Ljava/lang/Integer;
       257: invokevirtual #440                // Method java/util/HashMap.getOrDefault:(Ljava/lang/Object;Ljava/lang/Object;)Ljava/lang/Object;
       260: checkcast     #180                // class java/lang/Integer
       263: invokevirtual #464                // Method java/lang/Integer.intValue:()I
       266: invokestatic  #467                // Method com/chestterminal/util/NumberUtils.getFormatedBigNumber:(I)Ljava/lang/String;
       269: invokevirtual #96                 // Method com/hypixel/hytale/server/core/ui/builder/UICommandBuilder.set:(Ljava/lang/String;Ljava/lang/String;)Lcom/hypixel/hytale/server/core/ui/builder/UICommandBuilder;
       272: pop
       273: aload_3
       274: iload         5
       276: iload         6
       278: invokedynamic #472,  0            // InvokeDynamic #8:makeConcatWithConstants:(II)Ljava/lang/String;
       283: ldc_w         #473                // String Retrieve this item\n\nLeft Click: Full Stack\nRight Click: 1
       286: invokevirtual #96                 // Method com/hypixel/hytale/server/core/ui/builder/UICommandBuilder.set:(Ljava/lang/String;Ljava/lang/String;)Lcom/hypixel/hytale/server/core/ui/builder/UICommandBuilder;
       289: pop
       290: aload         4
       292: getstatic     #62                 // Field com/hypixel/hytale/protocol/packets/interface_/CustomUIEventBindingType.Activating:Lcom/hypixel/hytale/protocol/packets/interface_/CustomUIEventBindingType;
       295: iload         5
       297: iload         6
       299: invokedynamic #475,  0            // InvokeDynamic #9:makeConcatWithConstants:(II)Ljava/lang/String;
       304: ldc_w         #476                // String FindItem
       307: aload         8
       309: invokeinterface #295,  1          // InterfaceMethod java/util/Map$Entry.getKey:()Ljava/lang/Object;
       314: checkcast     #122                // class java/lang/String
       317: invokestatic  #74                 // Method com/hypixel/hytale/server/core/ui/builder/EventData.of:(Ljava/lang/String;Ljava/lang/String;)Lcom/hypixel/hytale/server/core/ui/builder/EventData;
       320: invokevirtual #478                // Method com/hypixel/hytale/server/core/ui/builder/UIEventBuilder.addEventBinding:(Lcom/hypixel/hytale/protocol/packets/interface_/CustomUIEventBindingType;Ljava/lang/String;Lcom/hypixel/hytale/server/core/ui/builder/EventData;)Lcom/hypixel/hytale/server/core/ui/builder/UIEventBuilder;
       323: pop
       324: aload         4
       326: getstatic     #62                 // Field com/hypixel/hytale/protocol/packets/interface_/CustomUIEventBindingType.Activating:Lcom/hypixel/hytale/protocol/packets/interface_/CustomUIEventBindingType;
       329: iload         5
       331: iload         6
       333: invokedynamic #481,  0            // InvokeDynamic #10:makeConcatWithConstants:(II)Ljava/lang/String;
       338: ldc_w         #482                // String GetItem
       341: aload         8
       343: invokeinterface #295,  1          // InterfaceMethod java/util/Map$Entry.getKey:()Ljava/lang/Object;
       348: checkcast     #122                // class java/lang/String
       351: aload         9
       353: invokevirtual #484                // Method com/hypixel/hytale/server/core/asset/type/item/config/Item.getMaxStack:()I
       356: invokedynamic #487,  0            // InvokeDynamic #11:makeConcatWithConstants:(Ljava/lang/String;I)Ljava/lang/String;
       361: invokestatic  #74                 // Method com/hypixel/hytale/server/core/ui/builder/EventData.of:(Ljava/lang/String;Ljava/lang/String;)Lcom/hypixel/hytale/server/core/ui/builder/EventData;
       364: invokevirtual #478                // Method com/hypixel/hytale/server/core/ui/builder/UIEventBuilder.addEventBinding:(Lcom/hypixel/hytale/protocol/packets/interface_/CustomUIEventBindingType;Ljava/lang/String;Lcom/hypixel/hytale/server/core/ui/builder/EventData;)Lcom/hypixel/hytale/server/core/ui/builder/UIEventBuilder;
       367: pop
       368: aload         4
       370: getstatic     #490                // Field com/hypixel/hytale/protocol/packets/interface_/CustomUIEventBindingType.RightClicking:Lcom/hypixel/hytale/protocol/packets/interface_/CustomUIEventBindingType;
       373: iload         5
       375: iload         6
       377: invokedynamic #481,  0            // InvokeDynamic #10:makeConcatWithConstants:(II)Ljava/lang/String;
       382: ldc_w         #482                // String GetItem
       385: aload         8
       387: invokeinterface #295,  1          // InterfaceMethod java/util/Map$Entry.getKey:()Ljava/lang/Object;
       392: checkcast     #122                // class java/lang/String
       395: invokedynamic #493,  0            // InvokeDynamic #12:makeConcatWithConstants:(Ljava/lang/String;)Ljava/lang/String;
       400: invokestatic  #74                 // Method com/hypixel/hytale/server/core/ui/builder/EventData.of:(Ljava/lang/String;Ljava/lang/String;)Lcom/hypixel/hytale/server/core/ui/builder/EventData;
       403: invokevirtual #478                // Method com/hypixel/hytale/server/core/ui/builder/UIEventBuilder.addEventBinding:(Lcom/hypixel/hytale/protocol/packets/interface_/CustomUIEventBindingType;Ljava/lang/String;Lcom/hypixel/hytale/server/core/ui/builder/EventData;)Lcom/hypixel/hytale/server/core/ui/builder/UIEventBuilder;
       406: pop
       407: iinc          6, 1
       410: iload         6
       412: bipush        8
       414: if_icmplt     423
       417: iconst_0
       418: istore        6
       420: iinc          5, 1
       423: goto          36
       426: return

  private void notifyNearbyItems(com.hypixel.hytale.server.core.universe.world.World, com.hypixel.hytale.component.Ref<com.hypixel.hytale.server.core.universe.world.storage.EntityStore>, com.hypixel.hytale.component.Store<com.hypixel.hytale.server.core.universe.world.storage.EntityStore>, int, java.lang.String);
    Code:
         0: new           #494                // class java/util/ArrayList
         3: dup
         4: invokespecial #496                // Method java/util/ArrayList."<init>":()V
         7: astore        6
         9: aload_3
        10: aload_2
        11: invokestatic  #497                // Method com/hypixel/hytale/server/core/modules/entity/component/TransformComponent.getComponentType:()Lcom/hypixel/hytale/component/ComponentType;
        14: invokevirtual #500                // Method com/hypixel/hytale/component/Store.getComponent:(Lcom/hypixel/hytale/component/Ref;Lcom/hypixel/hytale/component/ComponentType;)Lcom/hypixel/hytale/component/Component;
        17: checkcast     #498                // class com/hypixel/hytale/server/core/modules/entity/component/TransformComponent
        20: invokevirtual #501                // Method com/hypixel/hytale/server/core/modules/entity/component/TransformComponent.getPosition:()Lcom/hypixel/hytale/math/vector/Vector3d;
        23: astore        7
        25: iload         4
        27: ineg
        28: istore        8
        30: iload         8
        32: iload         4
        34: if_icmpgt     440
        37: iload         4
        39: ineg
        40: istore        9
        42: iload         9
        44: iload         4
        46: if_icmpge     434
        49: iload         4
        51: ineg
        52: istore        10
        54: iload         10
        56: iload         4
        58: if_icmpgt     428
        61: aload_1
        62: aload         7
        64: invokevirtual #505                // Method com/hypixel/hytale/math/vector/Vector3d.getX:()D
        67: iload         8
        69: i2d
        70: dadd
        71: d2i
        72: aload         7
        74: invokevirtual #511                // Method com/hypixel/hytale/math/vector/Vector3d.getY:()D
        77: iload         9
        79: i2d
        80: dadd
        81: d2i
        82: aload         7
        84: invokevirtual #514                // Method com/hypixel/hytale/math/vector/Vector3d.getZ:()D
        87: iload         10
        89: i2d
        90: dadd
        91: d2i
        92: iconst_1
        93: invokevirtual #517                // Method com/hypixel/hytale/server/core/universe/world/World.getState:(IIIZ)Lcom/hypixel/hytale/server/core/universe/world/meta/BlockState;
        96: astore        11
        98: aload         11
       100: instanceof    #523                // class com/hypixel/hytale/server/core/universe/world/meta/state/ItemContainerState
       103: ifeq          422
       106: aload         11
       108: checkcast     #523                // class com/hypixel/hytale/server/core/universe/world/meta/state/ItemContainerState
       111: astore        12
       113: aload         12
       115: invokevirtual #525                // Method com/hypixel/hytale/server/core/universe/world/meta/state/ItemContainerState.getItemContainer:()Lcom/hypixel/hytale/server/core/inventory/container/ItemContainer;
       118: astore        13
       120: aload         6
       122: aload         13
       124: invokevirtual #529                // Method java/util/ArrayList.contains:(Ljava/lang/Object;)Z
       127: ifeq          133
       130: goto          422
       133: aload         6
       135: aload         13
       137: invokevirtual #531                // Method java/util/ArrayList.add:(Ljava/lang/Object;)Z
       140: pop
       141: iconst_0
       142: istore        14
       144: iload         14
       146: aload         13
       148: invokevirtual #207                // Method com/hypixel/hytale/server/core/inventory/container/ItemContainer.getCapacity:()S
       151: if_icmpge     422
       154: aload         13
       156: iload         14
       158: invokevirtual #213                // Method com/hypixel/hytale/server/core/inventory/container/ItemContainer.getItemStack:(S)Lcom/hypixel/hytale/server/core/inventory/ItemStack;
       161: astore        15
       163: aload         15
       165: ifnull        412
       168: aload         15
       170: invokevirtual #217                // Method com/hypixel/hytale/server/core/inventory/ItemStack.isEmpty:()Z
       173: ifne          412
       176: aload         15
       178: invokevirtual #532                // Method com/hypixel/hytale/server/core/inventory/ItemStack.getItem:()Lcom/hypixel/hytale/server/core/asset/type/item/config/Item;
       181: invokevirtual #535                // Method com/hypixel/hytale/server/core/asset/type/item/config/Item.getId:()Ljava/lang/String;
       184: aload         5
       186: invokevirtual #121                // Method java/lang/String.equals:(Ljava/lang/Object;)Z
       189: ifeq          412
       192: aload         11
       194: invokevirtual #538                // Method com/hypixel/hytale/server/core/universe/world/meta/BlockState.getCenteredBlockPosition:()Lcom/hypixel/hytale/math/vector/Vector3d;
       197: astore        16
       199: getstatic     #543                // Field com/chestterminal/ChestTerminalPlugin.BOUNDING_BOXES:Ljava/util/Map;
       202: aload         11
       204: invokevirtual #546                // Method com/hypixel/hytale/server/core/universe/world/meta/BlockState.getBlockType:()Lcom/hypixel/hytale/server/core/asset/type/blocktype/config/BlockType;
       207: invokevirtual #550                // Method com/hypixel/hytale/server/core/asset/type/blocktype/config/BlockType.getHitboxType:()Ljava/lang/String;
       210: invokeinterface #555,  2          // InterfaceMethod java/util/Map.get:(Ljava/lang/Object;)Ljava/lang/Object;
       215: checkcast     #556                // class com/hypixel/hytale/server/core/asset/type/blockhitbox/BlockBoundingBoxes
       218: astore        17
       220: aload         17
       222: ifnull        412
       225: aload         17
       227: aload         11
       229: invokevirtual #558                // Method com/hypixel/hytale/server/core/universe/world/meta/BlockState.getRotationIndex:()I
       232: invokevirtual #561                // Method com/hypixel/hytale/server/core/asset/type/blockhitbox/BlockBoundingBoxes.get:(I)Lcom/hypixel/hytale/server/core/asset/type/blockhitbox/BlockBoundingBoxes$RotatedVariantBoxes;
       235: invokevirtual #564                // Method com/hypixel/hytale/server/core/asset/type/blockhitbox/BlockBoundingBoxes$RotatedVariantBoxes.getBoundingBox:()Lcom/hypixel/hytale/math/shape/Box;
       238: astore        18
       240: ldc_w         #570                // String DasEric_ChestTerminal_Custom_Alerted
       243: new           #506                // class com/hypixel/hytale/math/vector/Vector3d
       246: dup
       247: aload         16
       249: invokevirtual #505                // Method com/hypixel/hytale/math/vector/Vector3d.getX:()D
       252: aload         18
       254: invokevirtual #572                // Method com/hypixel/hytale/math/shape/Box.width:()D
       257: ldc2_w        #577                // double 2.0d
       260: ddiv
       261: dsub
       262: aload         16
       264: invokevirtual #511                // Method com/hypixel/hytale/math/vector/Vector3d.getY:()D
       267: ldc2_w        #579                // double 0.35d
       270: dsub
       271: aload         16
       273: invokevirtual #514                // Method com/hypixel/hytale/math/vector/Vector3d.getZ:()D
       276: invokespecial #581                // Method com/hypixel/hytale/math/vector/Vector3d."<init>":(DDD)V
       279: aload_3
       280: invokestatic  #584                // Method com/hypixel/hytale/server/core/universe/world/ParticleUtil.spawnParticleEffect:(Ljava/lang/String;Lcom/hypixel/hytale/math/vector/Vector3d;Lcom/hypixel/hytale/component/ComponentAccessor;)V
       283: ldc_w         #570                // String DasEric_ChestTerminal_Custom_Alerted
       286: new           #506                // class com/hypixel/hytale/math/vector/Vector3d
       289: dup
       290: aload         16
       292: invokevirtual #505                // Method com/hypixel/hytale/math/vector/Vector3d.getX:()D
       295: aload         18
       297: invokevirtual #572                // Method com/hypixel/hytale/math/shape/Box.width:()D
       300: ldc2_w        #577                // double 2.0d
       303: ddiv
       304: dadd
       305: aload         16
       307: invokevirtual #511                // Method com/hypixel/hytale/math/vector/Vector3d.getY:()D
       310: ldc2_w        #579                // double 0.35d
       313: dsub
       314: aload         16
       316: invokevirtual #514                // Method com/hypixel/hytale/math/vector/Vector3d.getZ:()D
       319: invokespecial #581                // Method com/hypixel/hytale/math/vector/Vector3d."<init>":(DDD)V
       322: aload_3
       323: invokestatic  #584                // Method com/hypixel/hytale/server/core/universe/world/ParticleUtil.spawnParticleEffect:(Ljava/lang/String;Lcom/hypixel/hytale/math/vector/Vector3d;Lcom/hypixel/hytale/component/ComponentAccessor;)V
       326: ldc_w         #570                // String DasEric_ChestTerminal_Custom_Alerted
       329: new           #506                // class com/hypixel/hytale/math/vector/Vector3d
       332: dup
       333: aload         16
       335: invokevirtual #505                // Method com/hypixel/hytale/math/vector/Vector3d.getX:()D
       338: aload         16
       340: invokevirtual #511                // Method com/hypixel/hytale/math/vector/Vector3d.getY:()D
       343: ldc2_w        #579                // double 0.35d
       346: dsub
       347: aload         16
       349: invokevirtual #514                // Method com/hypixel/hytale/math/vector/Vector3d.getZ:()D
       352: aload         18
       354: invokevirtual #590                // Method com/hypixel/hytale/math/shape/Box.depth:()D
       357: ldc2_w        #577                // double 2.0d
       360: ddiv
       361: dsub
       362: invokespecial #581                // Method com/hypixel/hytale/math/vector/Vector3d."<init>":(DDD)V
       365: aload_3
       366: invokestatic  #584                // Method com/hypixel/hytale/server/core/universe/world/ParticleUtil.spawnParticleEffect:(Ljava/lang/String;Lcom/hypixel/hytale/math/vector/Vector3d;Lcom/hypixel/hytale/component/ComponentAccessor;)V
       369: ldc_w         #570                // String DasEric_ChestTerminal_Custom_Alerted
       372: new           #506                // class com/hypixel/hytale/math/vector/Vector3d
       375: dup
       376: aload         16
       378: invokevirtual #505                // Method com/hypixel/hytale/math/vector/Vector3d.getX:()D
       381: aload         16
       383: invokevirtual #511                // Method com/hypixel/hytale/math/vector/Vector3d.getY:()D
       386: ldc2_w        #579                // double 0.35d
       389: dsub
       390: aload         16
       392: invokevirtual #514                // Method com/hypixel/hytale/math/vector/Vector3d.getZ:()D
       395: aload         18
       397: invokevirtual #590                // Method com/hypixel/hytale/math/shape/Box.depth:()D
       400: ldc2_w        #577                // double 2.0d
       403: ddiv
       404: dadd
       405: invokespecial #581                // Method com/hypixel/hytale/math/vector/Vector3d."<init>":(DDD)V
       408: aload_3
       409: invokestatic  #584                // Method com/hypixel/hytale/server/core/universe/world/ParticleUtil.spawnParticleEffect:(Ljava/lang/String;Lcom/hypixel/hytale/math/vector/Vector3d;Lcom/hypixel/hytale/component/ComponentAccessor;)V
       412: iload         14
       414: iconst_1
       415: iadd
       416: i2s
       417: istore        14
       419: goto          144
       422: iinc          10, 1
       425: goto          54
       428: iinc          9, 1
       431: goto          42
       434: iinc          8, 1
       437: goto          30
       440: return

  private void extractItems(com.hypixel.hytale.server.core.universe.world.World, com.hypixel.hytale.component.Ref<com.hypixel.hytale.server.core.universe.world.storage.EntityStore>, com.hypixel.hytale.component.Store<com.hypixel.hytale.server.core.universe.world.storage.EntityStore>, int, java.lang.String, int);
    Code:
         0: new           #494                // class java/util/ArrayList
         3: dup
         4: invokespecial #496                // Method java/util/ArrayList."<init>":()V
         7: astore        7
         9: aload_3
        10: aload_2
        11: invokestatic  #497                // Method com/hypixel/hytale/server/core/modules/entity/component/TransformComponent.getComponentType:()Lcom/hypixel/hytale/component/ComponentType;
        14: invokevirtual #500                // Method com/hypixel/hytale/component/Store.getComponent:(Lcom/hypixel/hytale/component/Ref;Lcom/hypixel/hytale/component/ComponentType;)Lcom/hypixel/hytale/component/Component;
        17: checkcast     #498                // class com/hypixel/hytale/server/core/modules/entity/component/TransformComponent
        20: invokevirtual #501                // Method com/hypixel/hytale/server/core/modules/entity/component/TransformComponent.getPosition:()Lcom/hypixel/hytale/math/vector/Vector3d;
        23: astore        8
        25: iconst_0
        26: istore        9
        28: iload         4
        30: ineg
        31: istore        10
        33: iload         10
        35: iload         4
        37: if_icmpgt     405
        40: iload         4
        42: ineg
        43: istore        11
        45: iload         11
        47: iload         4
        49: if_icmpge     399
        52: iload         4
        54: ineg
        55: istore        12
        57: iload         12
        59: iload         4
        61: if_icmpgt     393
        64: aload_2
        65: aload_1
        66: aload         8
        68: invokevirtual #505                // Method com/hypixel/hytale/math/vector/Vector3d.getX:()D
        71: iload         10
        73: i2d
        74: dadd
        75: d2i
        76: aload         8
        78: invokevirtual #511                // Method com/hypixel/hytale/math/vector/Vector3d.getY:()D
        81: iload         11
        83: i2d
        84: dadd
        85: d2i
        86: aload         8
        88: invokevirtual #514                // Method com/hypixel/hytale/math/vector/Vector3d.getZ:()D
        91: iload         12
        93: i2d
        94: dadd
        95: d2i
        96: invokestatic  #593                // Method com/chestterminal/util/InventoryUtils.isBlockInteractable:(Lcom/hypixel/hytale/component/Ref;Lcom/hypixel/hytale/server/core/universe/world/World;III)Z
        99: ifne          105
       102: goto          387
       105: aload_1
       106: aload         8
       108: invokevirtual #505                // Method com/hypixel/hytale/math/vector/Vector3d.getX:()D
       111: iload         10
       113: i2d
       114: dadd
       115: d2i
       116: aload         8
       118: invokevirtual #511                // Method com/hypixel/hytale/math/vector/Vector3d.getY:()D
       121: iload         11
       123: i2d
       124: dadd
       125: d2i
       126: aload         8
       128: invokevirtual #514                // Method com/hypixel/hytale/math/vector/Vector3d.getZ:()D
       131: iload         12
       133: i2d
       134: dadd
       135: d2i
       136: iconst_1
       137: invokevirtual #517                // Method com/hypixel/hytale/server/core/universe/world/World.getState:(IIIZ)Lcom/hypixel/hytale/server/core/universe/world/meta/BlockState;
       140: astore        13
       142: aload         13
       144: instanceof    #523                // class com/hypixel/hytale/server/core/universe/world/meta/state/ItemContainerState
       147: ifeq          387
       150: aload         13
       152: checkcast     #523                // class com/hypixel/hytale/server/core/universe/world/meta/state/ItemContainerState
       155: astore        14
       157: aload         14
       159: invokevirtual #525                // Method com/hypixel/hytale/server/core/universe/world/meta/state/ItemContainerState.getItemContainer:()Lcom/hypixel/hytale/server/core/inventory/container/ItemContainer;
       162: astore        15
       164: aload         7
       166: aload         15
       168: invokevirtual #529                // Method java/util/ArrayList.contains:(Ljava/lang/Object;)Z
       171: ifeq          177
       174: goto          387
       177: aload         7
       179: aload         15
       181: invokevirtual #531                // Method java/util/ArrayList.add:(Ljava/lang/Object;)Z
       184: pop
       185: iconst_0
       186: istore        16
       188: iload         16
       190: aload         15
       192: invokevirtual #207                // Method com/hypixel/hytale/server/core/inventory/container/ItemContainer.getCapacity:()S
       195: if_icmpge     387
       198: aload         15
       200: iload         16
       202: invokevirtual #213                // Method com/hypixel/hytale/server/core/inventory/container/ItemContainer.getItemStack:(S)Lcom/hypixel/hytale/server/core/inventory/ItemStack;
       205: astore        17
       207: aload         17
       209: ifnull        377
       212: aload         17
       214: invokevirtual #217                // Method com/hypixel/hytale/server/core/inventory/ItemStack.isEmpty:()Z
       217: ifne          377
       220: aload         17
       222: invokevirtual #532                // Method com/hypixel/hytale/server/core/inventory/ItemStack.getItem:()Lcom/hypixel/hytale/server/core/asset/type/item/config/Item;
       225: invokevirtual #535                // Method com/hypixel/hytale/server/core/asset/type/item/config/Item.getId:()Ljava/lang/String;
       228: aload         5
       230: invokevirtual #121                // Method java/lang/String.equals:(Ljava/lang/Object;)Z
       233: ifeq          377
       236: aload_3
       237: aload_2
       238: invokestatic  #239                // Method com/hypixel/hytale/server/core/entity/entities/Player.getComponentType:()Lcom/hypixel/hytale/component/ComponentType;
       241: invokevirtual #500                // Method com/hypixel/hytale/component/Store.getComponent:(Lcom/hypixel/hytale/component/Ref;Lcom/hypixel/hytale/component/ComponentType;)Lcom/hypixel/hytale/component/Component;
       244: checkcast     #240                // class com/hypixel/hytale/server/core/entity/entities/Player
       247: astore        18
       249: aload         18
       251: invokevirtual #597                // Method com/hypixel/hytale/server/core/entity/entities/Player.getInventory:()Lcom/hypixel/hytale/server/core/inventory/Inventory;
       254: invokevirtual #601                // Method com/hypixel/hytale/server/core/inventory/Inventory.getStorage:()Lcom/hypixel/hytale/server/core/inventory/container/ItemContainer;
       257: aload         17
       259: invokevirtual #606                // Method com/hypixel/hytale/server/core/inventory/container/ItemContainer.canAddItemStack:(Lcom/hypixel/hytale/server/core/inventory/ItemStack;)Z
       262: ifeq          377
       265: aload         15
       267: aload         17
       269: aload         17
       271: invokevirtual #610                // Method com/hypixel/hytale/server/core/inventory/ItemStack.getQuantity:()I
       274: iload         6
       276: invokestatic  #613                // Method java/lang/Math.min:(II)I
       279: invokevirtual #618                // Method com/hypixel/hytale/server/core/inventory/ItemStack.withQuantity:(I)Lcom/hypixel/hytale/server/core/inventory/ItemStack;
       282: invokevirtual #622                // Method com/hypixel/hytale/server/core/inventory/container/ItemContainer.removeItemStack:(Lcom/hypixel/hytale/server/core/inventory/ItemStack;)Lcom/hypixel/hytale/server/core/inventory/transaction/ItemStackTransaction;
       285: astore        19
       287: aload         19
       289: invokevirtual #626                // Method com/hypixel/hytale/server/core/inventory/transaction/ItemStackTransaction.succeeded:()Z
       292: ifeq          377
       295: aload         19
       297: invokevirtual #631                // Method com/hypixel/hytale/server/core/inventory/transaction/ItemStackTransaction.getQuery:()Lcom/hypixel/hytale/server/core/inventory/ItemStack;
       300: ifnull        377
       303: aload         18
       305: invokevirtual #597                // Method com/hypixel/hytale/server/core/entity/entities/Player.getInventory:()Lcom/hypixel/hytale/server/core/inventory/Inventory;
       308: invokevirtual #601                // Method com/hypixel/hytale/server/core/inventory/Inventory.getStorage:()Lcom/hypixel/hytale/server/core/inventory/container/ItemContainer;
       311: aload         19
       313: invokevirtual #631                // Method com/hypixel/hytale/server/core/inventory/transaction/ItemStackTransaction.getQuery:()Lcom/hypixel/hytale/server/core/inventory/ItemStack;
       316: invokevirtual #635                // Method com/hypixel/hytale/server/core/inventory/container/ItemContainer.addItemStack:(Lcom/hypixel/hytale/server/core/inventory/ItemStack;)Lcom/hypixel/hytale/server/core/inventory/transaction/ItemStackTransaction;
       319: pop
       320: iload         6
       322: aload         19
       324: invokevirtual #631                // Method com/hypixel/hytale/server/core/inventory/transaction/ItemStackTransaction.getQuery:()Lcom/hypixel/hytale/server/core/inventory/ItemStack;
       327: invokevirtual #610                // Method com/hypixel/hytale/server/core/inventory/ItemStack.getQuantity:()I
       330: isub
       331: istore        6
       333: iload         9
       335: ifne          371
       338: iconst_1
       339: istore        9
       341: invokestatic  #638                // Method com/hypixel/hytale/server/core/asset/type/soundevent/config/SoundEvent.getAssetMap:()Lcom/hypixel/hytale/assetstore/map/IndexedLookupTableAssetMap;
       344: ldc_w         #644                // String DasEric_ChestTerminal_SFX_Custom_Player_Pickup_Item
       347: invokevirtual #646                // Method com/hypixel/hytale/assetstore/map/IndexedLookupTableAssetMap.getIndex:(Ljava/lang/Object;)I
       350: istore        20
       352: aload_3
       353: aload_2
       354: invokestatic  #652                // Method com/hypixel/hytale/server/core/universe/PlayerRef.getComponentType:()Lcom/hypixel/hytale/component/ComponentType;
       357: invokevirtual #500                // Method com/hypixel/hytale/component/Store.getComponent:(Lcom/hypixel/hytale/component/Ref;Lcom/hypixel/hytale/component/ComponentType;)Lcom/hypixel/hytale/component/Component;
       360: checkcast     #349                // class com/hypixel/hytale/server/core/universe/PlayerRef
       363: iload         20
       365: getstatic     #653                // Field com/hypixel/hytale/protocol/SoundCategory.UI:Lcom/hypixel/hytale/protocol/SoundCategory;
       368: invokestatic  #659                // Method com/hypixel/hytale/server/core/universe/world/SoundUtil.playSoundEvent2dToPlayer:(Lcom/hypixel/hytale/server/core/universe/PlayerRef;ILcom/hypixel/hytale/protocol/SoundCategory;)V
       371: iload         6
       373: ifgt          377
       376: return
       377: iload         16
       379: iconst_1
       380: iadd
       381: i2s
       382: istore        16
       384: goto          188
       387: iinc          12, 1
       390: goto          57
       393: iinc          11, 1
       396: goto          45
       399: iinc          10, 1
       402: goto          33
       405: return

  public void handleDataEvent(com.hypixel.hytale.component.Ref, com.hypixel.hytale.component.Store, java.lang.Object);
    Code:
         0: aload_0
         1: aload_1
         2: aload_2
         3: aload_3
         4: checkcast     #2                  // class com/chestterminal/gui/UnifiedTerminalGui$TerminalGuiData
         7: invokevirtual #665                // Method handleDataEvent:(Lcom/hypixel/hytale/component/Ref;Lcom/hypixel/hytale/component/Store;Lcom/chestterminal/gui/UnifiedTerminalGui$TerminalGuiData;)V
        10: return

  private static void lambda$buildSearchList$0(java.util.HashMap, java.lang.String, java.lang.Integer);
    Code:
         0: aload_0
         1: aload_1
         2: getstatic     #668                // Field com/chestterminal/ChestTerminalPlugin.ITEMS:Ljava/util/Map;
         5: aload_1
         6: invokeinterface #555,  2          // InterfaceMethod java/util/Map.get:(Ljava/lang/Object;)Ljava/lang/Object;
        11: checkcast     #334                // class com/hypixel/hytale/server/core/asset/type/item/config/Item
        14: invokevirtual #671                // Method java/util/HashMap.put:(Ljava/lang/Object;Ljava/lang/Object;)Ljava/lang/Object;
        17: pop
        18: return

  static {};
    Code:
         0: ldc           #16                 // class com/chestterminal/gui/UnifiedTerminalGui
         2: invokevirtual #672                // Method java/lang/Class.desiredAssertionStatus:()Z
         5: ifne          12
         8: iconst_1
         9: goto          13
        12: iconst_0
        13: putstatic     #251                // Field $assertionsDisabled:Z
        16: return
}
