Picked up JAVA_TOOL_OPTIONS: -Dstdout.encoding=UTF-8 -Dstderr.encoding=UTF-8
Compiled from "PipePlugin.java"
public class com.example.plugin.PipePlugin extends com.hypixel.hytale.server.core.plugin.JavaPlugin {
  public static com.hypixel.hytale.component.ComponentType<com.hypixel.hytale.server.core.universe.world.storage.EntityStore, com.example.plugin.PipeComponent> PIPE_COMPONENT_TYPE;

  public com.example.plugin.PipePlugin(com.hypixel.hytale.server.core.plugin.JavaPluginInit);
    Code:
         0: aload_0
         1: aload_1
         2: invokespecial #1                  // Method com/hypixel/hytale/server/core/plugin/JavaPlugin."<init>":(Lcom/hypixel/hytale/server/core/plugin/JavaPluginInit;)V
         5: aload_0
         6: putstatic     #7                  // Field instance:Lcom/example/plugin/PipePlugin;
         9: aload_0
        10: new           #13                 // class com/example/plugin/network/PipeNetworkManager
        13: dup
        14: invokespecial #15                 // Method com/example/plugin/network/PipeNetworkManager."<init>":()V
        17: putfield      #18                 // Field pipeNetworkManager:Lcom/example/plugin/network/PipeNetworkManager;
        20: return

  public static com.example.plugin.PipePlugin getInstance();
    Code:
         0: getstatic     #7                  // Field instance:Lcom/example/plugin/PipePlugin;
         3: areturn

  public com.example.plugin.network.PipeNetworkManager getPipeNetworkManager();
    Code:
         0: aload_0
         1: getfield      #18                 // Field pipeNetworkManager:Lcom/example/plugin/network/PipeNetworkManager;
         4: areturn

  public com.example.plugin.PipeManager getPipeManager();
    Code:
         0: new           #22                 // class java/lang/UnsupportedOperationException
         3: dup
         4: ldc           #24                 // String PipeManager is deprecated. Use PipeNetworkManager.
         6: invokespecial #26                 // Method java/lang/UnsupportedOperationException."<init>":(Ljava/lang/String;)V
         9: athrow

  protected void setup();
    Code:
         0: aload_0
         1: invokespecial #29                 // Method com/hypixel/hytale/server/core/plugin/JavaPlugin.setup:()V
         4: aload_0
         5: invokevirtual #32                 // Method getEntityStoreRegistry:()Lcom/hypixel/hytale/component/ComponentRegistryProxy;
         8: ldc           #36                 // class com/example/plugin/PipeComponent
        10: ldc           #38                 // String pipe_data
        12: getstatic     #40                 // Field com/example/plugin/PipeComponent.CODEC:Lcom/hypixel/hytale/codec/builder/BuilderCodec;
        15: invokevirtual #44                 // Method com/hypixel/hytale/component/ComponentRegistryProxy.registerComponent:(Ljava/lang/Class;Ljava/lang/String;Lcom/hypixel/hytale/codec/builder/BuilderCodec;)Lcom/hypixel/hytale/component/ComponentType;
        18: putstatic     #50                 // Field PIPE_COMPONENT_TYPE:Lcom/hypixel/hytale/component/ComponentType;
        21: goto          37
        24: astore_1
        25: aload_1
        26: invokevirtual #56                 // Method java/lang/Exception.getMessage:()Ljava/lang/String;
        29: invokedynamic #60,  0             // InvokeDynamic #0:makeConcatWithConstants:(Ljava/lang/String;)Ljava/lang/String;
        34: invokestatic  #64                 // Method com/example/plugin/Broadcaster.log:(Ljava/lang/String;)V
        37: aload_0
        38: invokedynamic #69,  0             // InvokeDynamic #1:newThread:()Ljava/util/concurrent/ThreadFactory;
        43: invokestatic  #73                 // Method java/util/concurrent/Executors.newSingleThreadScheduledExecutor:(Ljava/util/concurrent/ThreadFactory;)Ljava/util/concurrent/ScheduledExecutorService;
        46: putfield      #79                 // Field tickExecutor:Ljava/util/concurrent/ScheduledExecutorService;
        49: aload_0
        50: getfield      #79                 // Field tickExecutor:Ljava/util/concurrent/ScheduledExecutorService;
        53: aload_0
        54: getfield      #18                 // Field pipeNetworkManager:Lcom/example/plugin/network/PipeNetworkManager;
        57: dup
        58: invokestatic  #83                 // Method java/util/Objects.requireNonNull:(Ljava/lang/Object;)Ljava/lang/Object;
        61: pop
        62: invokedynamic #89,  0             // InvokeDynamic #2:run:(Lcom/example/plugin/network/PipeNetworkManager;)Ljava/lang/Runnable;
        67: ldc2_w        #93                 // long 50l
        70: ldc2_w        #93                 // long 50l
        73: getstatic     #95                 // Field java/util/concurrent/TimeUnit.MILLISECONDS:Ljava/util/concurrent/TimeUnit;
        76: invokeinterface #101,  7          // InterfaceMethod java/util/concurrent/ScheduledExecutorService.scheduleAtFixedRate:(Ljava/lang/Runnable;JJLjava/util/concurrent/TimeUnit;)Ljava/util/concurrent/ScheduledFuture;
        81: pop
        82: aload_0
        83: invokevirtual #32                 // Method getEntityStoreRegistry:()Lcom/hypixel/hytale/component/ComponentRegistryProxy;
        86: new           #107                // class com/example/plugin/PipeSystems$PlaceSystem
        89: dup
        90: aload_0
        91: getfield      #18                 // Field pipeNetworkManager:Lcom/example/plugin/network/PipeNetworkManager;
        94: invokespecial #109                // Method com/example/plugin/PipeSystems$PlaceSystem."<init>":(Lcom/example/plugin/network/PipeNetworkManager;)V
        97: invokevirtual #112                // Method com/hypixel/hytale/component/ComponentRegistryProxy.registerSystem:(Lcom/hypixel/hytale/component/system/ISystem;)V
       100: aload_0
       101: invokevirtual #32                 // Method getEntityStoreRegistry:()Lcom/hypixel/hytale/component/ComponentRegistryProxy;
       104: new           #116                // class com/example/plugin/PipeSystems$BreakSystem
       107: dup
       108: aload_0
       109: getfield      #18                 // Field pipeNetworkManager:Lcom/example/plugin/network/PipeNetworkManager;
       112: invokespecial #118                // Method com/example/plugin/PipeSystems$BreakSystem."<init>":(Lcom/example/plugin/network/PipeNetworkManager;)V
       115: invokevirtual #112                // Method com/hypixel/hytale/component/ComponentRegistryProxy.registerSystem:(Lcom/hypixel/hytale/component/system/ISystem;)V
       118: aload_0
       119: invokevirtual #32                 // Method getEntityStoreRegistry:()Lcom/hypixel/hytale/component/ComponentRegistryProxy;
       122: new           #119                // class com/example/plugin/PipeUseBlockEventSystem
       125: dup
       126: invokespecial #121                // Method com/example/plugin/PipeUseBlockEventSystem."<init>":()V
       129: invokevirtual #112                // Method com/hypixel/hytale/component/ComponentRegistryProxy.registerSystem:(Lcom/hypixel/hytale/component/system/ISystem;)V
       132: goto          148
       135: astore_1
       136: aload_1
       137: invokevirtual #56                 // Method java/lang/Exception.getMessage:()Ljava/lang/String;
       140: invokedynamic #122,  0            // InvokeDynamic #3:makeConcatWithConstants:(Ljava/lang/String;)Ljava/lang/String;
       145: invokestatic  #64                 // Method com/example/plugin/Broadcaster.log:(Ljava/lang/String;)V
       148: aload_0
       149: invokevirtual #123                // Method getCommandRegistry:()Lcom/hypixel/hytale/server/core/command/system/CommandRegistry;
       152: new           #127                // class com/example/plugin/PipeCommand
       155: dup
       156: aload_0
       157: getfield      #18                 // Field pipeNetworkManager:Lcom/example/plugin/network/PipeNetworkManager;
       160: invokespecial #129                // Method com/example/plugin/PipeCommand."<init>":(Lcom/example/plugin/network/PipeNetworkManager;)V
       163: invokevirtual #130                // Method com/hypixel/hytale/server/core/command/system/CommandRegistry.registerCommand:(Lcom/hypixel/hytale/server/core/command/system/AbstractCommand;)Lcom/hypixel/hytale/server/core/command/system/CommandRegistration;
       166: pop
       167: goto          183
       170: astore_1
       171: aload_1
       172: invokevirtual #56                 // Method java/lang/Exception.getMessage:()Ljava/lang/String;
       175: invokedynamic #136,  0            // InvokeDynamic #4:makeConcatWithConstants:(Ljava/lang/String;)Ljava/lang/String;
       180: invokestatic  #64                 // Method com/example/plugin/Broadcaster.log:(Ljava/lang/String;)V
       183: aload_0
       184: getfield      #18                 // Field pipeNetworkManager:Lcom/example/plugin/network/PipeNetworkManager;
       187: invokevirtual #137                // Method com/example/plugin/network/PipeNetworkManager.loadNetworks:()V
       190: invokestatic  #140                // Method java/lang/Runtime.getRuntime:()Ljava/lang/Runtime;
       193: new           #146                // class java/lang/Thread
       196: dup
       197: aload_0
       198: invokedynamic #148,  0            // InvokeDynamic #5:run:(Lcom/example/plugin/PipePlugin;)Ljava/lang/Runnable;
       203: invokespecial #151                // Method java/lang/Thread."<init>":(Ljava/lang/Runnable;)V
       206: invokevirtual #154                // Method java/lang/Runtime.addShutdownHook:(Ljava/lang/Thread;)V
       209: getstatic     #158                // Field java/lang/System.out:Ljava/io/PrintStream;
       212: ldc           #164                // String PipePlugin setup complete with PipeNetworkManager!
       214: invokevirtual #166                // Method java/io/PrintStream.println:(Ljava/lang/String;)V
       217: return
      Exception table:
         from    to  target type
             4    21    24   Class java/lang/Exception
            82   132   135   Class java/lang/Exception
           148   167   170   Class java/lang/Exception
}
